coat/__init__.py
coat/fp8_trainer.py
coat/activation/__init__.py
coat/activation/utils.py
coat/activation/deepseek/fp8linear.py
coat/activation/deepseek/linear.py
coat/activation/fake_quantization/FloatPointQuantizeTorch.py
coat/activation/fake_quantization/FloatPointQuantizeTriton.py
coat/activation/fake_quantization/quantize_function.py
coat/activation/fake_quantization/utils.py
coat/activation/liger/cross_entropy.py
coat/activation/liger/utils.py
coat/activation/real_quantization/__init__.py
coat/activation/real_quantization/_dequantize.py
coat/activation/real_quantization/_division.py
coat/activation/real_quantization/_division_transpose.py
coat/activation/real_quantization/_memory_io.py
coat/activation/real_quantization/_quantize.py
coat/activation/real_quantization/_quantize_perblock.py
coat/activation/real_quantization/_quantize_perblock_transpose.py
coat/activation/real_quantization/_quantize_perblock_transpose_pergroup.py
coat/activation/real_quantization/_quantize_pertensor.py
coat/activation/real_quantization/_quantize_pertensor_transpose.py
coat/activation/real_quantization/_quantize_transpose.py
coat/activation/real_quantization/_transpose.py
coat/activation/real_quantization/add_bwd.py
coat/activation/real_quantization/add_fwd.py
coat/activation/real_quantization/common.py
coat/activation/real_quantization/fp8linear.py
coat/activation/real_quantization/func_layernorm_noparam.py
coat/activation/real_quantization/func_layernorm_param.py
coat/activation/real_quantization/func_quantize.py
coat/activation/real_quantization/func_rmsnorm.py
coat/activation/real_quantization/gelu_bwd.py
coat/activation/real_quantization/gelu_bwd_legacy.py
coat/activation/real_quantization/gelu_fwd.py
coat/activation/real_quantization/linear.py
coat/activation/real_quantization/mul_bwd.py
coat/activation/real_quantization/mul_bwd_legacy.py
coat/activation/real_quantization/mul_fwd.py
coat/activation/real_quantization/silu_bwd.py
fp8_coat-1.0.11.dist-info/licenses/LICENSE
fp8_coat-1.0.11.dist-info/METADATA
fp8_coat-1.0.11.dist-info/WHEEL
fp8_coat-1.0.11.dist-info/top_level.txt
fp8_coat-1.0.11.dist-info/RECORD
