Metadata-Version: 2.4
Name: fp8_coat
Version: 1.0.11
Summary: https://arxiv.org/abs/2410.19313. COAT: Compressing Optimizer states and Activation for Memory-Efficient FP8 Training
Project-URL: Homepage, https://github.com/NVlabs/COAT
Classifier: Programming Language :: Python :: 3
Requires-Python: >=3.9
License-File: LICENSE
Requires-Dist: torch>=2.4.1
Requires-Dist: triton==3.1.0
Requires-Dist: transformers==4.45.2
Requires-Dist: wandb==0.18.5
Requires-Dist: matplotlib==3.9.2
Requires-Dist: gdown==5.2.0
Requires-Dist: peft
Requires-Dist: sentencepiece
Requires-Dist: IPython
Dynamic: license-file
